odoo9_addon_keychain-9.0.1.0.0-py2.7-nspkg.pth
odoo_addons/keychain/__openerp__.py
odoo_addons/keychain/__init__.py
odoo_addons/keychain/README.rst
odoo_addons/keychain/security/ir.model.access.csv
odoo_addons/keychain/models/keychain.py
odoo_addons/keychain/models/__init__.py
odoo_addons/keychain/views/keychain_view.xml
odoo_addons/keychain/tests/test_keychain.py
odoo_addons/keychain/tests/__init__.py
odoo9_addon_keychain-9.0.1.0.0.dist-info/top_level.txt
odoo9_addon_keychain-9.0.1.0.0.dist-info/WHEEL
odoo9_addon_keychain-9.0.1.0.0.dist-info/RECORD
odoo9_addon_keychain-9.0.1.0.0.dist-info/metadata.json
odoo9_addon_keychain-9.0.1.0.0.dist-info/DESCRIPTION.rst
odoo9_addon_keychain-9.0.1.0.0.dist-info/METADATA
odoo9_addon_keychain-9.0.1.0.0.dist-info/namespace_packages.txt
